sammy/__init__.py
sammy/custom_properties.py
sammy/exceptions.py
sammy/tests.py
sammy/examples/__init__.py
sammy/examples/alexa_skill.py
sammy/examples/api_backend.py
sammy/examples/hello_world.py
sammy-0.4.3.dist-info/LICENSE
sammy-0.4.3.dist-info/METADATA
sammy-0.4.3.dist-info/WHEEL
sammy-0.4.3.dist-info/top_level.txt
sammy-0.4.3.dist-info/RECORD
