Metadata-Version: 2.1
Name: sammy
Version: 0.4.3
Summary: Python library for generating AWS SAM (Serverless Application Model) templates with validation.
Home-page: https://github.com/capless/sammy
Author: Brian Jinwright
Author-email: opensource@ipoots.com
Maintainer: Brian Jinwright
License: GNU General Public License v3.0
Keywords: serverless,cloudformation,sam
Platform: UNKNOWN
Classifier: Programming Language :: Python
Classifier: Topic :: Software Development :: Libraries :: Python Modules
Classifier: Environment :: Web Environment
Classifier: Programming Language :: Python :: 3.6
Classifier: Programming Language :: Python :: 3 :: Only
Requires-Dist: boto3 (>=1.9.93)
Requires-Dist: PyYAML (>=3.12)
Requires-Dist: valley (>=1.5.2)
